xmatters/__init__.py
xmatters/rest/__init__.py
xmatters/rest/api.py
xmatters/rest/audit.py
xmatters/rest/collection.py
xmatters/rest/device.py
xmatters/rest/dynamic_teams.py
xmatters/rest/event.py
xmatters/rest/group.py
xmatters/rest/libraries.py
xmatters/rest/oncall.py
xmatters/rest/person.py
xmatters/rest/plans.py
xmatters/rest/roster.py
xmatters/rest/shift.py
xmatters/rest/site.py
xmatters/util/__init__.py
xmatters/util/column.py
xmatters/util/timecalc.py
pyxmatters-0.1.3.6.dist-info/LICENSE
pyxmatters-0.1.3.6.dist-info/METADATA
pyxmatters-0.1.3.6.dist-info/WHEEL
pyxmatters-0.1.3.6.dist-info/top_level.txt
pyxmatters-0.1.3.6.dist-info/RECORD
