Metadata-Version: 2.1
Name: pyxmatters
Version: 0.1.3.6
Summary: pyxmatters
Home-page: http://github.com/matthewhenry1/pyxmatters
Author: Matt Henry
Author-email: mhenry@xmatters.com
License: MIT
Platform: UNKNOWN
Requires-Dist: requests
